Kyle_Smartsheet/SmartsheetTool.py
Kyle_Smartsheet/__init__.py
Kyle_Smartsheet-0.0.3.dist-info/METADATA
Kyle_Smartsheet-0.0.3.dist-info/WHEEL
Kyle_Smartsheet-0.0.3.dist-info/top_level.txt
Kyle_Smartsheet-0.0.3.dist-info/RECORD
