Metadata-Version: 2.1
Name: Kyle-Smartsheet
Version: 0.0.3
Summary: Connect Smartsheet with Dataframe
Author: kvuong
Author-email: vuong.chan.khang98@gmail.com
Keywords: smartsheet,kyle
Classifier: Development Status :: 1 - Planning
Classifier: Intended Audience :: Developers
Classifier: Programming Language :: Python :: 3
Classifier: Operating System :: Unix
Classifier: Operating System :: MacOS :: MacOS X
Classifier: Operating System :: Microsoft :: Windows
Requires-Dist: smartsheet-python-sdk
Requires-Dist: smartsheet-dataframe
Requires-Dist: pandas
